shell_whisperer/__init__.py
shell_whisperer/gpt_whisperer.py
shell_whisperer/main.py
shell_whisperer/utils.py
shell_whisperer-0.1.3.dist-info/METADATA
shell_whisperer-0.1.3.dist-info/WHEEL
shell_whisperer-0.1.3.dist-info/entry_points.txt
shell_whisperer-0.1.3.dist-info/RECORD
