Metadata-Version: 2.1
Name: shell-whisperer
Version: 0.1.3
Summary: Shell Whisperer is a command-line tool that generates CLI (Command Line Interface) commands based on natural language input.
License: MIT
Author: ishan
Author-email: ishannagpal554@gmail.com
Requires-Python: >=3.8,<4.0
Classifier: License :: OSI Approved :: MIT License
Classifier: Programming Language :: Python :: 3
Classifier: Programming Language :: Python :: 3.8
Classifier: Programming Language :: Python :: 3.9
Classifier: Programming Language :: Python :: 3.10
Classifier: Programming Language :: Python :: 3.11
Requires-Dist: openai (>=0.27.5,<0.28.0)
Requires-Dist: pyperclip (>=1.8.2,<2.0.0)
Requires-Dist: requests (>=2.29.0,<3.0.0)
Requires-Dist: rich (>=13.3.5,<14.0.0)
Requires-Dist: typer (>=0.8.0,<0.9.0)
